classy_vision/__init__.py
classy_vision/configs/r3d34_synthetic_video.json
classy_vision/configs/resnet50_synthetic_image_classy_config.json
classy_vision/configs/hmdb51/r3d34.json
classy_vision/configs/imagenet/densenet121_imagenet_classy_config.json
classy_vision/configs/imagenet/postactivated_r2d101.json
classy_vision/configs/imagenet/postactivated_r2d50.json
classy_vision/configs/imagenet/preactivated_r2d101.json
classy_vision/configs/imagenet/preactivated_r2d50.json
classy_vision/configs/imagenet/regnet_y_8gf_imagenet_classy_config.json
classy_vision/configs/imagenet/resnet101_imagenet_classy_config.json
classy_vision/configs/imagenet/resnet50_imagenet_classy_config.json
classy_vision/configs/imagenet/resnet50_label_smoothing_criterion.json
classy_vision/configs/imagenet/resnext101_32x4d_fine_tuning_config.json
classy_vision/configs/imagenet/resnext101_imagenet_classy_config.json
classy_vision/configs/imagenet/resnext50_imagenet_classy_config.json
classy_vision/configs/kinetics400/postactivated_i3d50.json
classy_vision/configs/kinetics400/postactivated_i3d50_fine_tuning.json
classy_vision/configs/kinetics400/preactivated_i3d50.json
classy_vision/configs/kinetics400/preactivated_i3d50_fine_tuning.json
classy_vision/configs/ucf101/r3d34.json
classy_vision/dataset/__init__.py
classy_vision/dataset/classy_cifar.py
classy_vision/dataset/classy_dataset.py
classy_vision/dataset/classy_hmdb51.py
classy_vision/dataset/classy_kinetics400.py
classy_vision/dataset/classy_synthetic_image.py
classy_vision/dataset/classy_synthetic_image_streaming.py
classy_vision/dataset/classy_synthetic_video.py
classy_vision/dataset/classy_ucf101.py
classy_vision/dataset/classy_video_dataset.py
classy_vision/dataset/dataloader_async_gpu_wrapper.py
classy_vision/dataset/dataloader_limit_wrapper.py
classy_vision/dataset/dataloader_skip_none_wrapper.py
classy_vision/dataset/dataloader_wrapper.py
classy_vision/dataset/image_path_dataset.py
classy_vision/dataset/core/__init__.py
classy_vision-0.7.0.dist-info/LICENSE
classy_vision-0.7.0.dist-info/METADATA
classy_vision-0.7.0.dist-info/NOTICE
classy_vision-0.7.0.dist-info/WHEEL
classy_vision-0.7.0.dist-info/top_level.txt
classy_vision-0.7.0.dist-info/RECORD
