Metadata-Version: 2.1
Name: classy-vision
Version: 0.7.0
Summary: An end-to-end PyTorch framework for image and video classification.
Home-page: https://classyvision.ai
License: MIT License
Project-URL: Documentation, https://classyvision.ai
Project-URL: Source, https://github.com/facebookresearch/ClassyVision
Keywords: deep learning,pytorch,AI
Classifier: Programming Language :: Python :: 3
Classifier: Programming Language :: Python :: 3.6
Classifier: License :: OSI Approved :: MIT License
Classifier: Operating System :: OS Independent
Classifier: Development Status :: 4 - Beta
Classifier: Intended Audience :: Developers
Classifier: Topic :: Scientific/Engineering :: Artificial Intelligence
Classifier: Topic :: Scientific/Engineering :: Image Recognition
Requires-Python: >=3.6
License-File: LICENSE
License-File: NOTICE
Requires-Dist: fvcore (>=0.1.3)
Requires-Dist: torch (>=1.6)
Requires-Dist: torchvision (>=0.7)
Provides-Extra: dev
Requires-Dist: GitPython ; extra == 'dev'
Requires-Dist: black (==19.3b0) ; extra == 'dev'
Requires-Dist: sphinx ; extra == 'dev'
Requires-Dist: isort (==5.2.2) ; extra == 'dev'
Requires-Dist: bs4 ; extra == 'dev'
Requires-Dist: nbconvert (==6.0.7) ; extra == 'dev'
Requires-Dist: pre-commit ; extra == 'dev'
Requires-Dist: parameterized ; extra == 'dev'
Requires-Dist: fairscale (==0.3.7) ; extra == 'dev'
